create_prism_mockserver/__init__.py
create_prism_mockserver/cli.py
create_prism_mockserver-0.1.1.dist-info/licenses/LICENSE
create_prism_mockserver-0.1.1.dist-info/METADATA
create_prism_mockserver-0.1.1.dist-info/WHEEL
create_prism_mockserver-0.1.1.dist-info/entry_points.txt
create_prism_mockserver-0.1.1.dist-info/top_level.txt
create_prism_mockserver-0.1.1.dist-info/RECORD
