Metadata-Version: 2.4
Name: create-prism-mockserver
Version: 0.1.1
Summary: CLI utility for setting up manifests which can be consumer by prism-mockerserver
Requires-Python: >=3.12
License-File: LICENSE
Requires-Dist: typer>=0.12.0
Requires-Dist: requests>=2.32.0
Dynamic: license-file
